[{"id":"2071","nom":"Le Rocher de Lisa","slug":null,"type":"appartement","occupancy":"6","bedrooms":"3","quartier":"Centre & proche centre","station":"Val Thorens","latitude":"45.29786","longitude":"6.57259","baths":0,"options":["Entretien et nettoyage quotidien (gouvernante)","Gestion du chalet, Organisation du s\u00e9jour et conciergerie","Service de navette (d\u00e9part et retour des pistes)","Service de navette","M\u00e9nage de fin de s\u00e9jour","Linge (draps et serviettes)","Lits faits \u00e0 l'arriv\u00e9e","Accueil \u00e0 la propri\u00e9t\u00e9","Produits de salle de bains","Chaussons"],"sejours":[{"debut":"2022-08-20","fin":"2022-08-27","status":"libre"},{"debut":"2022-08-27","fin":"2022-09-03","status":"libre"},{"debut":"2022-11-21","fin":"2022-11-28","status":"libre"},{"debut":"2022-11-28","fin":"2022-12-05","status":"libre"},{"debut":"2022-12-05","fin":"2022-12-12","status":"libre"},{"debut":"2022-12-12","fin":"2022-12-19","status":"libre"},{"debut":"2022-12-19","fin":"2022-12-26","status":"libre"},{"debut":"2022-12-26","fin":"2023-01-02","status":"libre"},{"debut":"2023-01-02","fin":"2023-01-09","status":"libre"},{"debut":"2023-01-09","fin":"2023-01-16","status":"libre"},{"debut":"2023-01-28","fin":"2023-02-04","status":"libre"},{"debut":"2023-02-04","fin":"2023-02-11","status":"libre"},{"debut":"2023-02-11","fin":"2023-02-18","status":"libre"},{"debut":"2023-02-18","fin":"2023-02-25","status":"libre"},{"debut":"2023-02-25","fin":"2023-03-04","status":"libre"},{"debut":"2023-03-04","fin":"2023-03-11","status":"libre"},{"debut":"2023-03-11","fin":"2023-03-18","status":"libre"},{"debut":"2023-03-18","fin":"2023-03-25","status":"libre"},{"debut":"2023-03-25","fin":"2023-04-01","status":"libre"},{"debut":"2023-04-01","fin":"2023-04-08","status":"libre"},{"debut":"2023-04-08","fin":"2023-04-15","status":"libre"},{"debut":"2023-04-15","fin":"2023-04-22","status":"libre"},{"debut":"2023-04-22","fin":"2023-04-29","status":"libre"},{"debut":"2023-04-29","fin":"2023-05-06","status":"libre"}],"photos":[{"url":"https:\/\/admin.cimalpes.com\/photos\/bien\/2071\/appartement_le_rocher_de_lisa_val_thorens_06.jpg","ext":"jpg","id":"appartement_le_rocher_de_lisa_val_thorens_06","width":2000,"height":1331},{"url":"https:\/\/admin.cimalpes.com\/photos\/bien\/2071\/appartement_le_rocher_de_lisa_val_thorens.jpg","ext":"jpg","id":"appartement_le_rocher_de_lisa_val_thorens","width":2000,"height":1331},{"url":"https:\/\/admin.cimalpes.com\/photos\/bien\/2071\/80-rocher_de_lisa-loc-cimalpes-valtho-web-4.jpg","ext":"jpg","id":"80-rocher_de_lisa-loc-cimalpes-valtho-web-4","width":4016,"height":2673},{"url":"https:\/\/admin.cimalpes.com\/photos\/bien\/2071\/appartement_le_rocher_de_lisa_val_thorens_10.jpg","ext":"jpg","id":"appartement_le_rocher_de_lisa_val_thorens_10","width":2000,"height":1331},{"url":"https:\/\/admin.cimalpes.com\/photos\/bien\/2071\/appartement_le_rocher_de_lisa_val_thorens_02.jpg","ext":"jpg","id":"appartement_le_rocher_de_lisa_val_thorens_02","width":2000,"height":1331},{"url":"https:\/\/admin.cimalpes.com\/photos\/bien\/2071\/appartement_le_rocher_de_lisa_val_thorens_03.jpg","ext":"jpg","id":"appartement_le_rocher_de_lisa_val_thorens_03","width":2000,"height":1331},{"url":"https:\/\/admin.cimalpes.com\/photos\/bien\/2071\/appartement_le_rocher_de_lisa_val_thorens_04.jpg","ext":"jpg","id":"appartement_le_rocher_de_lisa_val_thorens_04","width":2000,"height":1331},{"url":"https:\/\/admin.cimalpes.com\/photos\/bien\/2071\/appartement_le_rocher_de_lisa_val_thorens_05.jpg","ext":"jpg","id":"appartement_le_rocher_de_lisa_val_thorens_05","width":2000,"height":1331},{"url":"https:\/\/admin.cimalpes.com\/photos\/bien\/2071\/appartement_le_rocher_de_lisa_val_thorens_07.jpg","ext":"jpg","id":"appartement_le_rocher_de_lisa_val_thorens_07","width":2000,"height":1331},{"url":"https:\/\/admin.cimalpes.com\/photos\/bien\/2071\/80-rocher_de_lisa-loc-cimalpes-valtho-web-3.jpg","ext":"jpg","id":"80-rocher_de_lisa-loc-cimalpes-valtho-web-3","width":4581,"height":3049},{"url":"https:\/\/admin.cimalpes.com\/photos\/bien\/2071\/80-rocher_de_lisa-loc-cimalpes-valtho-web-2.jpg","ext":"jpg","id":"80-rocher_de_lisa-loc-cimalpes-valtho-web-2","width":4588,"height":3054},{"url":"https:\/\/admin.cimalpes.com\/photos\/bien\/2071\/appartement_le_rocher_de_lisa_val_thorens_08.jpg","ext":"jpg","id":"appartement_le_rocher_de_lisa_val_thorens_08","width":2000,"height":1331},{"url":"https:\/\/admin.cimalpes.com\/photos\/bien\/2071\/appartement_le_rocher_de_lisa_val_thorens_11.jpg","ext":"jpg","id":"appartement_le_rocher_de_lisa_val_thorens_11","width":2000,"height":1331},{"url":"https:\/\/admin.cimalpes.com\/photos\/bien\/2071\/appartement_le_rocher_de_lisa_val_thorens_09.jpg","ext":"jpg","id":"appartement_le_rocher_de_lisa_val_thorens_09","width":2000,"height":1331},{"url":"https:\/\/admin.cimalpes.com\/photos\/bien\/2071\/appartement_le_rocher_de_lisa_val_thorens_12.jpg","ext":"jpg","id":"appartement_le_rocher_de_lisa_val_thorens_12","width":2000,"height":1331},{"url":"https:\/\/admin.cimalpes.com\/photos\/bien\/2071\/appartement_le_rocher_de_lisa_val_thorens_13.jpg","ext":"jpg","id":"appartement_le_rocher_de_lisa_val_thorens_13","width":2000,"height":1331},{"url":"https:\/\/admin.cimalpes.com\/photos\/bien\/2071\/appartement_le_rocher_de_lisa_val_thorens_14.jpg","ext":"jpg","id":"appartement_le_rocher_de_lisa_val_thorens_14","width":2000,"height":1331},{"url":"https:\/\/admin.cimalpes.com\/photos\/bien\/2071\/appartement_le_rocher_de_lisa_val_thorens_15.jpg","ext":"jpg","id":"appartement_le_rocher_de_lisa_val_thorens_15","width":2000,"height":1331}],"updatedAt":null,"chambres":[{"nom":"","id":"4897","type":1,"etage":1,"equipments":["Dressing","TV","Douche","S\u00e8che-cheveux","S\u00e8che-serviettes","Simple vasque","Toilettes"],"lits":[{"quantite":"2","largeur":"190","charac_1":"Lit simple ","charac_2":"possibilit\u00e9 lit double"}]},{"nom":"","id":"4898","type":1,"etage":1,"equipments":["Dressing","TV","Douche","S\u00e8che-cheveux","S\u00e8che-serviettes","Simple vasque","Toilettes","Commode"],"lits":[{"quantite":"2","largeur":"190","charac_1":"Lit simple ","charac_2":"possibilit\u00e9 lit double"}]},{"nom":"","id":"4899","type":1,"etage":1,"equipments":["Dressing","TV","Douche","S\u00e8che-cheveux","S\u00e8che-serviettes","Simple vasque","Toilettes","Commode"],"lits":[{"quantite":"1","largeur":"190","charac_1":"Lit simple ","charac_2":"possibilit\u00e9 lit double"}]}],"prices":[{"debut":"2022-08-20","fin":"2022-08-27","min_stay":"7","saison":"","semaine":"","prices":{"price":172,"nb_chambre":"3","nb_nuit":1}},{"debut":"2022-08-27","fin":"2022-09-03","min_stay":"7","saison":"","semaine":"","prices":{"price":172,"nb_chambre":"3","nb_nuit":1}},{"debut":"2022-11-21","fin":"2022-11-28","min_stay":"7","saison":"","semaine":"","prices":{"price":272,"nb_chambre":"3","nb_nuit":1}},{"debut":"2022-11-28","fin":"2022-12-05","min_stay":"7","saison":"","semaine":"","prices":{"price":272,"nb_chambre":"3","nb_nuit":1}},{"debut":"2022-12-05","fin":"2022-12-12","min_stay":"7","saison":"","semaine":"","prices":{"price":272,"nb_chambre":"3","nb_nuit":1}},{"debut":"2022-12-12","fin":"2022-12-19","min_stay":"7","saison":"","semaine":"","prices":{"price":329,"nb_chambre":"3","nb_nuit":1}},{"debut":"2022-12-19","fin":"2022-12-26","min_stay":"7","saison":"","semaine":"","prices":{"price":500,"nb_chambre":"3","nb_nuit":1}},{"debut":"2022-12-26","fin":"2023-01-02","min_stay":"7","saison":"","semaine":"","prices":{"price":600,"nb_chambre":"3","nb_nuit":1}},{"debut":"2023-01-02","fin":"2023-01-09","min_stay":"7","saison":"","semaine":"","prices":{"price":400,"nb_chambre":"3","nb_nuit":1}},{"debut":"2023-01-09","fin":"2023-01-16","min_stay":"7","saison":"","semaine":"","prices":{"price":329,"nb_chambre":"3","nb_nuit":1}},{"debut":"2023-01-28","fin":"2023-02-04","min_stay":"7","saison":"","semaine":"","prices":{"price":415,"nb_chambre":"3","nb_nuit":1}},{"debut":"2023-02-04","fin":"2023-02-11","min_stay":"7","saison":"","semaine":"","prices":{"price":500,"nb_chambre":"3","nb_nuit":1}},{"debut":"2023-02-11","fin":"2023-02-18","min_stay":"7","saison":"","semaine":"","prices":{"price":558,"nb_chambre":"3","nb_nuit":1}},{"debut":"2023-02-18","fin":"2023-02-25","min_stay":"7","saison":"","semaine":"","prices":{"price":558,"nb_chambre":"3","nb_nuit":1}},{"debut":"2023-02-25","fin":"2023-03-04","min_stay":"7","saison":"","semaine":"","prices":{"price":500,"nb_chambre":"3","nb_nuit":1}},{"debut":"2023-03-04","fin":"2023-03-11","min_stay":"7","saison":"","semaine":"","prices":{"price":400,"nb_chambre":"3","nb_nuit":1}},{"debut":"2023-03-11","fin":"2023-03-18","min_stay":"7","saison":"","semaine":"","prices":{"price":329,"nb_chambre":"3","nb_nuit":1}},{"debut":"2023-03-18","fin":"2023-03-25","min_stay":"7","saison":"","semaine":"","prices":{"price":329,"nb_chambre":"3","nb_nuit":1}},{"debut":"2023-03-25","fin":"2023-04-01","min_stay":"7","saison":"","semaine":"","prices":{"price":372,"nb_chambre":"3","nb_nuit":1}},{"debut":"2023-04-01","fin":"2023-04-08","min_stay":"7","saison":"","semaine":"","prices":{"price":372,"nb_chambre":"3","nb_nuit":1}},{"debut":"2023-04-08","fin":"2023-04-15","min_stay":"7","saison":"","semaine":"","prices":{"price":372,"nb_chambre":"3","nb_nuit":1}},{"debut":"2023-04-15","fin":"2023-04-22","min_stay":"7","saison":"","semaine":"","prices":{"price":329,"nb_chambre":"3","nb_nuit":1}},{"debut":"2023-04-22","fin":"2023-04-29","min_stay":"7","saison":"","semaine":"","prices":{"price":329,"nb_chambre":"3","nb_nuit":1}},{"debut":"2023-04-29","fin":"2023-05-06","min_stay":"7","saison":"","semaine":"","prices":{"price":272,"nb_chambre":"3","nb_nuit":1}}],"equipments":["Sauna","Cuisine \u00e9quip\u00e9e","Cuisine ouverte","Espace repas","Po\u00eale \u00e0 bois","Salon","Terrasse","TV","Micro-onde","R\u00e9frig\u00e9rateur","Cafeti\u00e8re Nespresso","Wok","Bouilloire","Grille pain","Plaques de cuisson vitroc\u00e9ramiques","Four","Garage","Place de parking","Mobilier d'ext\u00e9rieur"],"descriptionBref":{"fr":"Situ\u00e9 \u00e0 l'entr\u00e9e de la station de Val Thorens, \u00e0 une centaine de m\u00e8tres du premier d\u00e9part des pistes, l'appartement \"Le Rocher de Lisa\" est id\u00e9al pour un s\u00e9jour entre amis ou pour une petite famille.\nLa terrasse, \u00e9quip\u00e9e d'un sauna, offre une vue panoramique sur la vall\u00e9e des Belleville.","en":"Located at the entrance of the resort of Val Thorens, a hundred meters from the first departure of the slopes, the apartment \"Le Rocher de Lisa\" is ideal for a stay with friends or for a small family.\nThe terrace, equipped with a sauna, offers a panoramic view on the Belleville valley."},"descriptionCourt":{"fr":"Organisez votre s\u00e9jour sans vous pr\u00e9occuper ni du linge de maison ni de vos lits \u00e0 votre arriv\u00e9e.\nNous accordons une attention particuli\u00e8re aux d\u00e9tails qui font toute la diff\u00e9rence. D\u00e9couvrez notre service Essential et ses petites attentions qui vous attendent pour vous donner le sourire d\u00e8s votre arriv\u00e9e et faciliter votre s\u00e9jour !\n","en":"Organise your stay without having to worry about linen or beds on arrival. We pay special attention to the details that make all the difference.\nDiscover our Essential service and the little extra touches that will put a smile on your face on arrival and make your stay easier."},"distances":{"centre":{"value":1.1,"unit":1,"time":"","time_unit":"","time_per":""},"ecole_ski":{"value":1.1,"unit":1,"time":"","time_unit":"","time_per":""},"piste":{"value":0.15,"unit":1,"time":"","time_unit":"","time_per":""},"telesiege":{"value":0.15,"unit":1,"time":"","time_unit":"","time_per":""}}},{"id":"2107","nom":"Vanoise 265","slug":null,"type":"appartement","occupancy":"2","bedrooms":"2","quartier":"Centre & proche centre","station":"Val Thorens","latitude":"45.29828","longitude":"6.58171","baths":0,"options":["Entretien et nettoyage quotidien (gouvernante)","Gestion du chalet, Organisation du s\u00e9jour et conciergerie","Service de navette (d\u00e9part et retour des pistes)","Service de navette","M\u00e9nage de fin de s\u00e9jour","Accueil en agence","Linge (draps et serviettes)","Lits faits \u00e0 l'arriv\u00e9e","Produits de salle de bains","Chaussons"],"sejours":[{"debut":"2022-08-20","fin":"2022-08-27","status":"libre"},{"debut":"2022-08-27","fin":"2022-09-03","status":"libre"},{"debut":"2022-11-21","fin":"2022-11-28","status":"libre"},{"debut":"2022-11-28","fin":"2022-12-05","status":"libre"},{"debut":"2022-12-05","fin":"2022-12-12","status":"libre"},{"debut":"2022-12-12","fin":"2022-12-19","status":"libre"},{"debut":"2022-12-19","fin":"2022-12-26","status":"libre"},{"debut":"2022-12-26","fin":"2023-01-02","status":"libre"},{"debut":"2023-01-02","fin":"2023-01-09","status":"libre"},{"debut":"2023-01-09","fin":"2023-01-16","status":"libre"},{"debut":"2023-01-28","fin":"2023-02-04","status":"libre"},{"debut":"2023-02-04","fin":"2023-02-11","status":"libre"},{"debut":"2023-02-11","fin":"2023-02-18","status":"libre"},{"debut":"2023-02-18","fin":"2023-02-25","status":"libre"},{"debut":"2023-02-25","fin":"2023-03-04","status":"libre"},{"debut":"2023-03-04","fin":"2023-03-11","status":"libre"},{"debut":"2023-03-11","fin":"2023-03-18","status":"libre"},{"debut":"2023-03-18","fin":"2023-03-25","status":"libre"},{"debut":"2023-03-25","fin":"2023-04-01","status":"libre"},{"debut":"2023-04-01","fin":"2023-04-08","status":"libre"},{"debut":"2023-04-08","fin":"2023-04-15","status":"libre"},{"debut":"2023-04-15","fin":"2023-04-22","status":"libre"},{"debut":"2023-04-22","fin":"2023-04-29","status":"libre"},{"debut":"2023-04-29","fin":"2023-05-06","status":"libre"}],"photos":[{"url":"https:\/\/admin.cimalpes.com\/photos\/bien\/2107\/d43_9089-modifier.jpg","ext":"jpg","id":"d43_9089-modifier","width":1999,"height":1331},{"url":"https:\/\/admin.cimalpes.com\/photos\/bien\/2107\/d43_9094-modifier.jpg","ext":"jpg","id":"d43_9094-modifier","width":2000,"height":1331},{"url":"https:\/\/admin.cimalpes.com\/photos\/bien\/2107\/d43_9101-hdr-modifier.jpg","ext":"jpg","id":"d43_9101-hdr-modifier","width":2000,"height":1331},{"url":"https:\/\/admin.cimalpes.com\/photos\/bien\/2107\/d43_9106-hdr-modifier.jpg","ext":"jpg","id":"d43_9106-hdr-modifier","width":2000,"height":1331},{"url":"https:\/\/admin.cimalpes.com\/photos\/bien\/2107\/d43_9111-hdr-modifier.jpg","ext":"jpg","id":"d43_9111-hdr-modifier","width":2000,"height":1331},{"url":"https:\/\/admin.cimalpes.com\/photos\/bien\/2107\/d43_9114-modifier.jpg","ext":"jpg","id":"d43_9114-modifier","width":2000,"height":1331},{"url":"https:\/\/admin.cimalpes.com\/photos\/bien\/2107\/d43_9119-modifier.jpg","ext":"jpg","id":"d43_9119-modifier","width":2000,"height":1331},{"url":"https:\/\/admin.cimalpes.com\/photos\/bien\/2107\/d43_9122-modifier.jpg","ext":"jpg","id":"d43_9122-modifier","width":2000,"height":1331},{"url":"https:\/\/admin.cimalpes.com\/photos\/bien\/2107\/d43_9130-modifier.jpg","ext":"jpg","id":"d43_9130-modifier","width":2000,"height":1331},{"url":"https:\/\/admin.cimalpes.com\/photos\/bien\/2107\/d43_9136-hdr-modifier-modifier.jpg","ext":"jpg","id":"d43_9136-hdr-modifier-modifier","width":2000,"height":1331}],"updatedAt":null,"chambres":[{"nom":"","id":"4985","type":1,"etage":0,"equipments":[],"lits":[{"quantite":"1","largeur":"190","charac_1":"Lits superpos\u00e9s ","charac_2":"deux couchages "}]},{"nom":"","id":"4986","type":1,"etage":0,"equipments":[],"lits":[{"quantite":"1","largeur":"200","charac_1":"Lit double","charac_2":""}]}],"prices":[{"debut":"2022-08-20","fin":"2022-08-27","min_stay":"7","saison":"","semaine":"","prices":{"price":72,"nb_chambre":"2","nb_nuit":1}},{"debut":"2022-08-27","fin":"2022-09-03","min_stay":"7","saison":"","semaine":"","prices":{"price":72,"nb_chambre":"2","nb_nuit":1}},{"debut":"2022-11-21","fin":"2022-11-28","min_stay":"7","saison":"","semaine":"","prices":{"price":179,"nb_chambre":"2","nb_nuit":1}},{"debut":"2022-11-28","fin":"2022-12-05","min_stay":"7","saison":"","semaine":"","prices":{"price":179,"nb_chambre":"2","nb_nuit":1}},{"debut":"2022-12-05","fin":"2022-12-12","min_stay":"7","saison":"","semaine":"","prices":{"price":179,"nb_chambre":"2","nb_nuit":1}},{"debut":"2022-12-12","fin":"2022-12-19","min_stay":"7","saison":"","semaine":"","prices":{"price":186,"nb_chambre":"2","nb_nuit":1}},{"debut":"2022-12-19","fin":"2022-12-26","min_stay":"7","saison":"","semaine":"","prices":{"price":272,"nb_chambre":"2","nb_nuit":1}},{"debut":"2022-12-26","fin":"2023-01-02","min_stay":"7","saison":"","semaine":"","prices":{"price":336,"nb_chambre":"2","nb_nuit":1}},{"debut":"2023-01-02","fin":"2023-01-09","min_stay":"7","saison":"","semaine":"","prices":{"price":250,"nb_chambre":"2","nb_nuit":1}},{"debut":"2023-01-09","fin":"2023-01-16","min_stay":"7","saison":"","semaine":"","prices":{"price":186,"nb_chambre":"2","nb_nuit":1}},{"debut":"2023-01-28","fin":"2023-02-04","min_stay":"7","saison":"","semaine":"","prices":{"price":250,"nb_chambre":"2","nb_nuit":1}},{"debut":"2023-02-04","fin":"2023-02-11","min_stay":"7","saison":"","semaine":"","prices":{"price":322,"nb_chambre":"2","nb_nuit":1}},{"debut":"2023-02-11","fin":"2023-02-18","min_stay":"7","saison":"","semaine":"","prices":{"price":336,"nb_chambre":"2","nb_nuit":1}},{"debut":"2023-02-18","fin":"2023-02-25","min_stay":"7","saison":"","semaine":"","prices":{"price":336,"nb_chambre":"2","nb_nuit":1}},{"debut":"2023-02-25","fin":"2023-03-04","min_stay":"7","saison":"","semaine":"","prices":{"price":322,"nb_chambre":"2","nb_nuit":1}},{"debut":"2023-03-04","fin":"2023-03-11","min_stay":"7","saison":"","semaine":"","prices":{"price":250,"nb_chambre":"2","nb_nuit":1}},{"debut":"2023-03-11","fin":"2023-03-18","min_stay":"7","saison":"","semaine":"","prices":{"price":250,"nb_chambre":"2","nb_nuit":1}},{"debut":"2023-03-18","fin":"2023-03-25","min_stay":"7","saison":"","semaine":"","prices":{"price":250,"nb_chambre":"2","nb_nuit":1}},{"debut":"2023-03-25","fin":"2023-04-01","min_stay":"7","saison":"","semaine":"","prices":{"price":236,"nb_chambre":"2","nb_nuit":1}},{"debut":"2023-04-01","fin":"2023-04-08","min_stay":"7","saison":"","semaine":"","prices":{"price":236,"nb_chambre":"2","nb_nuit":1}},{"debut":"2023-04-08","fin":"2023-04-15","min_stay":"7","saison":"","semaine":"","prices":{"price":236,"nb_chambre":"2","nb_nuit":1}},{"debut":"2023-04-15","fin":"2023-04-22","min_stay":"7","saison":"","semaine":"","prices":{"price":236,"nb_chambre":"2","nb_nuit":1}},{"debut":"2023-04-22","fin":"2023-04-29","min_stay":"7","saison":"","semaine":"","prices":{"price":186,"nb_chambre":"2","nb_nuit":1}},{"debut":"2023-04-29","fin":"2023-05-06","min_stay":"7","saison":"","semaine":"","prices":{"price":179,"nb_chambre":"2","nb_nuit":1}}],"equipments":["Canap\u00e9 convertible","Kitchenette","TV","Micro-onde","R\u00e9frig\u00e9rateur","Plaques de cuisson \u00e9lectriques","Hotte de cuisine","Bouilloire","Lave-vaisselle","Four"],"descriptionBref":{"fr":"L'appartement Vanoise 265 est situ\u00e9 dans la rue commer\u00e7ante et tr\u00e8s proche du premier d\u00e9part des pistes.\nSitu\u00e9 au deuxi\u00e8me \u00e9tage avec ascenseur d'une r\u00e9sidence en plein c\u009cur de Val Thorens, cet appartement offre une facilit\u00e9 d'acc\u00e8s \u00e0 toutes les commodit\u00e9s.","en":"The apartment Vanoise 265 is located in the shopping street and very close to the first departure of the slopes.\nLocated on the second floor with lift of a residence in the heart of Val Thorens, this apartment offers an easy access to all amenities."},"descriptionCourt":{"fr":"Organisez votre s\u00e9jour sans vous pr\u00e9occuper ni du linge de maison ni de vos lits \u00e0 votre arriv\u00e9e.\nNous accordons une attention particuli\u00e8re aux d\u00e9tails qui font toute la diff\u00e9rence. D\u00e9couvrez notre service Essential et ses petites attentions qui vous attendent pour vous donner le sourire d\u00e8s votre arriv\u00e9e et faciliter votre s\u00e9jour !\n","en":"Organise your stay without having to worry about linen or beds on arrival. We pay special attention to the details that make all the difference.\nDiscover our Essential service and the little extra touches that will put a smile on your face on arrival and make your stay easier."},"distances":{"centre":{"value":0,"unit":1,"time":"","time_unit":"","time_per":""},"ecole_ski":{"value":0.01,"unit":1,"time":"","time_unit":"","time_per":""},"piste":{"value":0.05,"unit":1,"time":"","time_unit":"","time_per":""},"telesiege":{"value":0.2,"unit":1,"time":"","time_unit":"","time_per":""}}}]